setup.py
spinnaker_spinner.egg-info/.gitignore
spinnaker_spinner.egg-info/PKG-INFO
spinnaker_spinner.egg-info/SOURCES.txt
spinnaker_spinner.egg-info/dependency_links.txt
spinnaker_spinner.egg-info/entry_points.txt
spinnaker_spinner.egg-info/requires.txt
spinnaker_spinner.egg-info/top_level.txt
spinner/__init__.py
spinner/board.py
spinner/cabinet.py
spinner/coordinates.py
spinner/metrics.py
spinner/plan.py
spinner/probe.py
spinner/proxy.py
spinner/timing_logger.py
spinner/topology.py
spinner/transforms.py
spinner/utils.py
spinner/version.py
spinner/diagrams/__init__.py
spinner/diagrams/interactive_wiring_guide.py
spinner/diagrams/machine.py
spinner/diagrams/machine_map.py
spinner/scripts/__init__.py
spinner/scripts/arguments.py
spinner/scripts/contexts.py
spinner/scripts/ethernet_chips.py
spinner/scripts/machine_map.py
spinner/scripts/markdown_gen.py
spinner/scripts/proxy_server.py
spinner/scripts/topology_stats.py
spinner/scripts/wiring_diagram.py
spinner/scripts/wiring_guide.py
spinner/scripts/wiring_list.py
spinner/scripts/wiring_stats.py
spinner/scripts/wiring_validator.py