Metadata-Version: 1.0
Name: spinnaker-spinner
Version: 2.5.0
Summary: A tool for generating wiring instructions for large SpiNNaker machines.
Home-page: UNKNOWN
Author: Jonathan Heathcote
Author-email: UNKNOWN
License: GPLv2
Platform: UNKNOWN
